{
  "f8e6b000-5643-4b86-9080-aa680ce1f599": {
    "asset": 1537416991000,
    "meta": 1537416991000,
    "relativePath": "image"
  },
  "fc09f9bd-2cce-4605-b630-8145ef809ed6": {
    "asset": 1537416991000,
    "meta": 1537416991000,
    "relativePath": "misc"
  },
  "f6e6dd15-71d1-4ffe-ace7-24fd39942c05": {
    "asset": 1537416991000,
    "meta": 1537416991000,
    "relativePath": "obsolete"
  },
  "f743d2b6-b7ea-4c14-a55b-547ed4d0a045": {
    "asset": 1537416991000,
    "meta": 1537416991000,
    "relativePath": "particle"
  },
  "ae6c6c98-11e4-452f-8758-75f5c6a56e83": {
    "asset": 1537416991000,
    "meta": 1537416991000,
    "relativePath": "prefab"
  },
  "701fb184-3a99-4395-8acb-adaabfd0bf1a": {
    "asset": 1541513138456,
    "meta": 1540188215382,
    "relativePath": "textures"
  },
  "a90cdc53-a8be-42b4-82d8-9ff676dad3c9": {
    "asset": 1540188238342,
    "meta": 1540188238422,
    "relativePath": "textures/1.png"
  },
  "36e38186-c176-423b-95ec-14f0759c5cdc": {
    "asset": 1540188238342,
    "meta": 1540188238426,
    "relativePath": "textures/0.png"
  },
  "607fc7d6-6db5-40f8-abf9-642d50cb7364": {
    "asset": 1540188238342,
    "meta": 1540188238458,
    "relativePath": "textures/2.png"
  },
  "fdd541fc-f2c1-4419-be52-8804df5cd9e3": {
    "asset": 1540188238342,
    "meta": 1540188238466,
    "relativePath": "textures/4.png"
  },
  "a991debe-03fd-461e-a046-efbf34e9d5e3": {
    "asset": 1540188238342,
    "meta": 1540188238490,
    "relativePath": "textures/5.png"
  },
  "d0a5c952-35d7-49df-a905-4ca7d251ef1b": {
    "asset": 1540188238342,
    "meta": 1540188238506,
    "relativePath": "textures/3.png"
  },
  "7615031d-8c37-4cf4-a06e-ef55ba6269e1": {
    "asset": 1540188238343,
    "meta": 1540188238520,
    "relativePath": "textures/6.png"
  },
  "0b872378-929e-44e4-a05a-1e10ee5f8a48": {
    "asset": 1540188238343,
    "meta": 1540188238546,
    "relativePath": "textures/7.png"
  },
  "95d06d69-31a8-4b0c-9cab-f28eebc159b9": {
    "asset": 1540188238343,
    "meta": 1540188238564,
    "relativePath": "textures/8.png"
  },
  "d543b130-f818-47ae-9fe8-d27a91bd79a3": {
    "asset": 1540188238343,
    "meta": 1540188238584,
    "relativePath": "textures/9.png"
  },
  "a11c5528-3641-4648-90a2-8dff67ab2044": {
    "asset": 1540188238343,
    "meta": 1540188238601,
    "relativePath": "textures/10.png"
  },
  "97fe8850-37d0-4186-9802-5c7113be386d": {
    "asset": 1540188238343,
    "meta": 1540188238611,
    "relativePath": "textures/11.png"
  },
  "393fa646-a106-4277-98dc-187364b65571": {
    "asset": 1540188238343,
    "meta": 1540188238628,
    "relativePath": "textures/12.png"
  },
  "17492573-591a-4f1d-8061-00bc1bb1f52c": {
    "asset": 1540188238344,
    "meta": 1540188238646,
    "relativePath": "textures/13.png"
  },
  "6161a142-b6de-4e56-ae46-1759690bbbb1": {
    "asset": 1540188238344,
    "meta": 1540188238657,
    "relativePath": "textures/14.png"
  },
  "8f0fd606-4162-4d47-929e-b343b365dad7": {
    "asset": 1540188238344,
    "meta": 1540188238674,
    "relativePath": "textures/16.png"
  },
  "fee68090-35a4-4439-a541-15e64b364476": {
    "asset": 1540188238344,
    "meta": 1540188238684,
    "relativePath": "textures/17.png"
  },
  "a1318019-5999-414b-877a-bfb2a503d459": {
    "asset": 1540188238344,
    "meta": 1540188238704,
    "relativePath": "textures/15.png"
  },
  "73af7636-3355-479e-9255-4f950c3be1fe": {
    "asset": 1540188238344,
    "meta": 1540188238716,
    "relativePath": "textures/18.png"
  },
  "c9aaf610-d505-4f39-9661-16f32f921a7e": {
    "asset": 1540188238344,
    "meta": 1540188238731,
    "relativePath": "textures/19.png"
  },
  "b89e4f4a-841d-40fb-84a0-24e8cd33f321": {
    "asset": 1540188238344,
    "meta": 1540188238747,
    "relativePath": "textures/20.png"
  },
  "4c19c663-da5a-488e-970d-06ccdea819fe": {
    "asset": 1540188238344,
    "meta": 1540188238764,
    "relativePath": "textures/21.png"
  },
  "7850d742-3d16-4185-b19a-94c2f9d2f258": {
    "asset": 1540188238344,
    "meta": 1540188238783,
    "relativePath": "textures/22.png"
  },
  "3b439a2f-738f-43f2-8593-88d8272ef699": {
    "asset": 1540188238345,
    "meta": 1540188238801,
    "relativePath": "textures/23.png"
  },
  "7a7ec65a-0e2e-4501-945d-1faef97ebff4": {
    "asset": 1540188238345,
    "meta": 1540188238810,
    "relativePath": "textures/24.png"
  },
  "8e869290-74d6-45a9-b298-ab5bc988603a": {
    "asset": 1540188238345,
    "meta": 1540188238828,
    "relativePath": "textures/25.png"
  },
  "f0d89087-c37c-4f00-817d-dc137758a672": {
    "asset": 1540188238345,
    "meta": 1540188238848,
    "relativePath": "textures/27.png"
  },
  "fe0771a3-97d5-429e-83b7-1807c774a993": {
    "asset": 1540188238345,
    "meta": 1540188238859,
    "relativePath": "textures/26.png"
  },
  "3c460125-f66b-42c1-a71d-94e2aa788f62": {
    "asset": 1540188238345,
    "meta": 1540188238876,
    "relativePath": "textures/28.png"
  },
  "e5e01fdb-ce4c-49c5-8211-e9d79dfff1c7": {
    "asset": 1540188238345,
    "meta": 1540188238892,
    "relativePath": "textures/30.png"
  },
  "53604ed8-7d4a-485f-8609-17be211305df": {
    "asset": 1540188238345,
    "meta": 1540188238904,
    "relativePath": "textures/29.png"
  },
  "cc99a828-42c0-4a3c-a5c9-68cd828d94ac": {
    "asset": 1540188238345,
    "meta": 1540188238919,
    "relativePath": "textures/31.png"
  },
  "883391b5-17ee-4ce9-ab94-36b6cf7891c7": {
    "asset": 1540188238345,
    "meta": 1540188238938,
    "relativePath": "textures/32.png"
  },
  "c1fe6cd6-58f6-4d5b-bebc-a8bf2f478951": {
    "asset": 1540188238345,
    "meta": 1540188238950,
    "relativePath": "textures/33.png"
  },
  "bb9422d2-bfc2-47ed-939b-791216342f5c": {
    "asset": 1541511844894,
    "meta": 1540188468800,
    "relativePath": "scenes"
  },
  "1fc5f44f-539a-4316-a523-d0adaf39cb5d": {
    "asset": 1541515097429,
    "meta": 1541515097439,
    "relativePath": "scenes/game.fire"
  },
  "15a56eef-08da-44c1-8702-5438611d1c54": {
    "asset": 1540197848704,
    "meta": 1540193254081,
    "relativePath": "scripts"
  },
  "317847b0-c4b0-415e-bec7-0196139ed84b": {
    "asset": 1540198115184,
    "meta": 1540198116965,
    "relativePath": "scripts/Line.js"
  },
  "d4d008bc-f8c2-4208-91d7-420f67865865": {
    "asset": 1540272722182,
    "meta": 1540272722187,
    "relativePath": "Pai.prefab"
  },
  "69f30123-769f-4c0d-8d58-2f4560ebb6af": {
    "asset": 1540299998706,
    "meta": 1540300001332,
    "relativePath": "scripts/Pai.js"
  },
  "ce699e26-b652-44ac-a9e3-4229bf87e9b7": {
    "asset": 1540305081686,
    "meta": 1540305081729,
    "relativePath": "textures/34.png"
  },
  "7564f787-30f6-44e8-9174-fe4be6ce66d7": {
    "asset": 1541513138449,
    "meta": 1541513138555,
    "relativePath": "textures/tutorial.png"
  },
  "71561142-4c83-4933-afca-cb7a17f67053": {
    "asset": 1537416991000,
    "meta": 1541513928176,
    "relativePath": "image/default_btn_disabled.png"
  },
  "e851e89b-faa2-4484-bea6-5c01dd9f06e2": {
    "asset": 1537416991000,
    "meta": 1541513928179,
    "relativePath": "image/default_btn_normal.png"
  },
  "edd215b9-2796-4a05-aaf5-81f96c9281ce": {
    "asset": 1537416991000,
    "meta": 1541513928191,
    "relativePath": "image/default_editbox_bg.png"
  },
  "b43ff3c2-02bb-4874-81f7-f2dea6970f18": {
    "asset": 1537416991000,
    "meta": 1541513928192,
    "relativePath": "image/default_btn_pressed.png"
  },
  "d81ec8ad-247c-4e62-aa3c-d35c4193c7af": {
    "asset": 1537416991000,
    "meta": 1541513928200,
    "relativePath": "image/default_panel.png"
  },
  "99170b0b-d210-46f1-b213-7d9e3f23098a": {
    "asset": 1537416991000,
    "meta": 1541513928202,
    "relativePath": "image/default_progressbar_bg.png"
  },
  "cfef78f1-c8df-49b7-8ed0-4c953ace2621": {
    "asset": 1537416991000,
    "meta": 1541513928211,
    "relativePath": "image/default_progressbar.png"
  },
  "567dcd80-8bf4-4535-8a5a-313f1caf078a": {
    "asset": 1537416991000,
    "meta": 1541513928213,
    "relativePath": "image/default_radio_button_off.png"
  },
  "4bab67cb-18e6-4099-b840-355f0473f890": {
    "asset": 1537416991000,
    "meta": 1541513928223,
    "relativePath": "image/default_scrollbar_bg.png"
  },
  "9d60001f-b5f4-4726-a629-2659e3ded0b8": {
    "asset": 1537416991000,
    "meta": 1541513928223,
    "relativePath": "image/default_radio_button_on.png"
  },
  "617323dd-11f4-4dd3-8eec-0caf6b3b45b9": {
    "asset": 1537416991000,
    "meta": 1541513928231,
    "relativePath": "image/default_scrollbar_vertical_bg.png"
  },
  "d6d3ca85-4681-47c1-b5dd-d036a9d39ea2": {
    "asset": 1537416991000,
    "meta": 1541513928232,
    "relativePath": "image/default_scrollbar_vertical.png"
  },
  "0275e94c-56a7-410f-bd1a-fc7483f7d14a": {
    "asset": 1537416991000,
    "meta": 1541513928239,
    "relativePath": "image/default_sprite_splash.png"
  },
  "0291c134-b3da-4098-b7b5-e397edbe947f": {
    "asset": 1537416991000,
    "meta": 1541513928241,
    "relativePath": "image/default_scrollbar.png"
  },
  "6e056173-d285-473c-b206-40a7fff5386e": {
    "asset": 1537416991000,
    "meta": 1541513928250,
    "relativePath": "image/default_sprite.png"
  },
  "73a0903d-d80e-4e3c-aa67-f999543c08f5": {
    "asset": 1537416991000,
    "meta": 1541513928252,
    "relativePath": "image/default_toggle_checkmark.png"
  },
  "d29077ba-1627-4a72-9579-7b56a235340c": {
    "asset": 1537416991000,
    "meta": 1541513928260,
    "relativePath": "image/default_toggle_normal.png"
  },
  "c25b9d50-c8fc-4d27-beeb-6e7c1f2e5c0f": {
    "asset": 1537416991000,
    "meta": 1541513928261,
    "relativePath": "image/default_toggle_disabled.png"
  },
  "2be36297-9abb-4fee-8049-9ed5e271da8a": {
    "asset": 1537416991000,
    "meta": 1541513928266,
    "relativePath": "misc/default_video.mp4"
  },
  "b181c1e4-0a72-4a91-bfb0-ae6f36ca60bd": {
    "asset": 1537416991000,
    "meta": 1541513928269,
    "relativePath": "image/default_toggle_pressed.png"
  },
  "b8223619-7e38-47c4-841f-9160c232495a": {
    "asset": 1537416991000,
    "meta": 1541513928969,
    "relativePath": "obsolete/atom.plist"
  },
  "8a96b965-2dc0-4e03-aa90-3b79cb93b5b4": {
    "asset": 1537416991000,
    "meta": 1541513928277,
    "relativePath": "obsolete/atom.png"
  },
  "b2687ac4-099e-403c-a192-ff477686f4f5": {
    "asset": 1537416991000,
    "meta": 1541513928971,
    "relativePath": "particle/atom.plist"
  },
  "d0a82d39-bede-46c4-b698-c81ff0dedfff": {
    "asset": 1537416991000,
    "meta": 1541513928279,
    "relativePath": "particle/atom.png"
  },
  "972b9a4d-47ee-4c74-b5c3-61d8a69bc29f": {
    "asset": 1537416991000,
    "meta": 1541513928282,
    "relativePath": "prefab/button.prefab"
  },
  "2c937608-2562-40ea-b264-7395df6f0cea": {
    "asset": 1537416991000,
    "meta": 1541513928282,
    "relativePath": "prefab/canvas.prefab"
  },
  "61aeb05b-3b32-452b-8eed-2b76deeed554": {
    "asset": 1537416991000,
    "meta": 1541513928284,
    "relativePath": "prefab/editbox.prefab"
  },
  "27756ebb-3d33-44b0-9b96-e858fadd4dd4": {
    "asset": 1537416991000,
    "meta": 1541513928285,
    "relativePath": "prefab/label.prefab"
  },
  "785a442c-3ceb-45be-a46e-7317f625f3b9": {
    "asset": 1537416991000,
    "meta": 1541513928287,
    "relativePath": "prefab/layout.prefab"
  },
  "ca8401fe-ad6e-41a8-bd46-8e3e4e9945be": {
    "asset": 1537416991000,
    "meta": 1541513928288,
    "relativePath": "prefab/pageview.prefab"
  },
  "cd33edea-55f5-46c2-958d-357a01384a36": {
    "asset": 1537416991000,
    "meta": 1541513928291,
    "relativePath": "prefab/particlesystem.prefab"
  },
  "5965ffac-69da-4b55-bcde-9225d0613c28": {
    "asset": 1537416991000,
    "meta": 1541513928291,
    "relativePath": "prefab/progressBar.prefab"
  },
  "4a37dd57-78cd-4cec-aad4-f11a73d12b63": {
    "asset": 1537416991000,
    "meta": 1541513928294,
    "relativePath": "prefab/richtext.prefab"
  },
  "32044bd2-481f-4cf1-a656-e2b2fb1594eb": {
    "asset": 1537416991000,
    "meta": 1541513928295,
    "relativePath": "prefab/scrollview.prefab"
  },
  "0004d1cf-a0ad-47d8-ab17-34d3db9d35a3": {
    "asset": 1537416991000,
    "meta": 1541513928297,
    "relativePath": "prefab/slider.prefab"
  },
  "1f55e3be-b89b-4b79-88de-47fd31018044": {
    "asset": 1537416991000,
    "meta": 1541513928298,
    "relativePath": "prefab/sprite_splash.prefab"
  },
  "96083d03-c332-4a3f-9386-d03e2d19e8ee": {
    "asset": 1537416991000,
    "meta": 1541513928300,
    "relativePath": "prefab/sprite.prefab"
  },
  "7de03a80-4457-438d-95a7-3e7cdffd6086": {
    "asset": 1537416991000,
    "meta": 1541513928300,
    "relativePath": "prefab/tiledmap.prefab"
  },
  "0e42ba95-1fa1-46aa-b2cf-143cd1bcee2c": {
    "asset": 1537416991000,
    "meta": 1541513928302,
    "relativePath": "prefab/tiledtile.prefab"
  },
  "0d784963-d024-4ea6-a7db-03be0ad63010": {
    "asset": 1537416991000,
    "meta": 1541513928303,
    "relativePath": "prefab/toggle.prefab"
  },
  "bf0a434c-84dd-4a8e-a08a-7a36f180cc75": {
    "asset": 1537416991000,
    "meta": 1541513928304,
    "relativePath": "prefab/toggleContainer.prefab"
  },
  "d1b8be49-b0a0-435c-83b7-552bed4bbe35": {
    "asset": 1537416991000,
    "meta": 1541513928306,
    "relativePath": "prefab/toggleGroup.prefab"
  },
  "232d2782-c4bd-4bb4-9e01-909f03d6d3b9": {
    "asset": 1537416991000,
    "meta": 1541513928307,
    "relativePath": "prefab/videoplayer.prefab"
  },
  "8c5001fd-07ee-4a4b-a8a0-63e15195e94d": {
    "asset": 1537416991000,
    "meta": 1541513928943,
    "relativePath": "prefab/webview.prefab"
  },
  "0751e630-ff6d-48c1-b547-36b32b3bbb8c": {
    "asset": 1541515017870,
    "meta": 1541515022963,
    "relativePath": "scripts/game.js"
  }
}